snowflake/core/__init__.py
snowflake/core/_constants.py
snowflake/core/_http_requests.py
snowflake/core/_identifiers.py
snowflake/core/_operation.py
snowflake/core/_options.py
snowflake/core/_rest_connection.py
snowflake/core/_root.py
snowflake/core/_thread_pool.py
snowflake/core/_utils.py
snowflake/core/exceptions.py
snowflake/core/logging.py
snowflake/core/py.typed
snowflake/core/rest.py
snowflake/core/version.py
snowflake/core/_common/__init__.py
snowflake/core/_common/account_collection.py
snowflake/core/_common/base_collection.py
snowflake/core/_common/database_collection.py
snowflake/core/_common/models.py
snowflake/core/_common/schema_collection.py
snowflake/core/_generated/__init__.py
snowflake/core/_generated/api_client.py
snowflake/core/_generated/configuration.py
snowflake/core/_generated/paging.py
snowflake/core/_generated/rest.py
snowflake/core/_internal/__init__.py
snowflake/core/_internal/client_info.py
snowflake/core/_internal/pydantic_compatibility.py
snowflake/core/_internal/root_configuration.py
snowflake/core/_internal/snowapi_parameters.py
snowflake/core/_internal/telemetry.py
snowflake/core/_internal/utils.py
snowflake/core/account/__init__.py
snowflake/core/account/_account.py
snowflake/core/account/_generated/__init__.py
snowflake/core/account/_generated/api/__init__.py
snowflake/core/account/_generated/api/account_api.py
snowflake/core/account/_generated/api/account_api_base.py
snowflake/core/account/_generated/models/__init__.py
snowflake/core/account/_generated/models/account.py
snowflake/core/account/_generated/models/error_response.py
snowflake/core/account/_generated/models/success_accepted_response.py
snowflake/core/account/_generated/models/success_response.py
snowflake/core/alert/__init__.py
snowflake/core/alert/_alert.py
snowflake/core/alert/_generated/__init__.py
snowflake/core/alert/_generated/api/__init__.py
snowflake/core/alert/_generated/api/alert_api.py
snowflake/core/alert/_generated/models/__init__.py
snowflake_core-1.10.0.dist-info/METADATA
snowflake_core-1.10.0.dist-info/WHEEL
snowflake_core-1.10.0.dist-info/licenses/LICENSE
snowflake_core-1.10.0.dist-info/RECORD
